whyis_fediverse/__init__.py
whyis_fediverse/plugin.py
whyis_fediverse/test_example.trig
whyis_fediverse/test_example.ttl
whyis_fediverse/vocab.ttl
whyis_fediverse/static/js/#new_post.js#
whyis_fediverse/static/js/comment.js
whyis_fediverse/static/js/discussion.js
whyis_fediverse/static/js/new_post.js
whyis_fediverse/static/js/post.js
whyis_fediverse/static/js/post_view.js
whyis_fediverse/static/js/selectable.js
whyis_fediverse/static/js/selectable.js~
whyis_fediverse/static/js/selections.js
whyis_fediverse/static/js/selections.js~
whyis_fediverse/templates/__init__.py
whyis_fediverse/templates/all_discussion.html
whyis_fediverse/templates/all_discussion.html~
whyis_fediverse/templates/all_discussion.json
whyis_fediverse/templates/discussion.html
whyis_fediverse/templates/discussion.json
whyis_fediverse/templates/embed_image.html
whyis_fediverse/templates/embed_image.html~
whyis_fediverse/templates/embed_object.html
whyis_fediverse/templates/embed_object.html~
whyis_fediverse/templates/embed_resource.html
whyis_fediverse/templates/embed_resource.html~
whyis_fediverse/templates/embed_video.html
whyis_fediverse/templates/embed_video.html~
whyis_fediverse/templates/image_embed.html
whyis_fediverse/templates/image_embed.svg
whyis_fediverse/templates/object_data.json
whyis_fediverse/templates/object_replies.json
whyis_fediverse/templates/object_view.html
whyis_fediverse/templates/resource_get.json
whyis_fediverse/templates/resource_search.json
whyis_fediverse/templates/space_get.json
whyis_fediverse/templates/space_search.json
whyis_fediverse-0.4.4.dist-info/LICENSE
whyis_fediverse-0.4.4.dist-info/METADATA
whyis_fediverse-0.4.4.dist-info/WHEEL
whyis_fediverse-0.4.4.dist-info/entry_points.txt
whyis_fediverse-0.4.4.dist-info/top_level.txt
whyis_fediverse-0.4.4.dist-info/RECORD
