Metadata-Version: 2.1
Name: whyis-fediverse
Version: 0.4.4
License-File: LICENSE
Requires-Dist: whyis
